NumLex/__init__.py
NumLex/data_struct/__intit__.py
NumLex/data_struct/circ_que.py
NumLex/data_struct/simp_que.py
NumLex/data_struct/simp_stk.py
NumLex/m/__init__.py
NumLex/m/arith.py
NumLex/m/geo.py
NumLex/m/prob.py
NumLex/m/stats.py
NumLex/num_ops/__init__.py
NumLex/num_ops/num_ops.py
NumLex/str_ops/__init__.py
NumLex/str_ops/str_ops.py
NumLex/temp/__init__.py
NumLex/temp/temp.py
NumLex-2.0.0.dist-info/LICENSE
NumLex-2.0.0.dist-info/METADATA
NumLex-2.0.0.dist-info/WHEEL
NumLex-2.0.0.dist-info/top_level.txt
NumLex-2.0.0.dist-info/RECORD
