Metadata-Version: 2.1
Name: NumLex
Version: 2.0.0
Summary: A blend of 'Numerical' and 'Lexical' indicating the dual focus on numbers and language.
Home-page: https://github.com/Jenil-Desai/NumLex
Author: Jenil Desai
Author-email: Jenil Desai <jenildev91@gmail.com>
Project-URL: Homepage, https://github.com/Jenil-Desai/NumLex
Project-URL: Issues, https://github.com/Jenil-Desai/NumLex/issues
Classifier: Programming Language :: Python :: 3
Classifier: License :: OSI Approved :: MIT License
Classifier: Operating System :: OS Independent
Requires-Python: >=3.8
License-File: LICENSE
